[{"sura_id":2,"aya_id":62,"segs":[{"y":11,"x":13,"w":1223,"h":117},{"y":146,"x":15,"w":1221,"h":122},{"y":285,"x":347,"w":889,"h":133}]},{"sura_id":2,"aya_id":63,"segs":[{"y":279,"x":15,"w":239,"h":110},{"y":416,"x":14,"w":1222,"h":117},{"y":554,"x":320,"w":915,"h":117}]},{"sura_id":2,"aya_id":64,"segs":[{"y":542,"x":14,"w":220,"h":118},{"y":684,"x":13,"w":1223,"h":115},{"y":827,"x":1031,"w":205,"h":119}]},{"sura_id":2,"aya_id":65,"segs":[{"y":818,"x":13,"w":932,"h":117},{"y":947,"x":581,"w":655,"h":117}]},{"sura_id":2,"aya_id":66,"segs":[{"y":958,"x":15,"w":479,"h":100},{"y":1095,"x":292,"w":943,"h":103}]},{"sura_id":2,"aya_id":67,"segs":[{"y":1099,"x":13,"w":184,"h":95},{"y":1216,"x":12,"w":1223,"h":121},{"y":1350,"x":85,"w":1150,"h":125}]},{"sura_id":2,"aya_id":68,"segs":[{"y":1489,"x":15,"w":1223,"h":127},{"y":1621,"x":14,"w":1221,"h":125},{"y":1765,"x":1052,"w":184,"h":103}]},{"sura_id":2,"aya_id":69,"segs":[{"y":1751,"x":14,"w":951,"h":130},{"y":1892,"x":87,"w":1148,"h":134}]}]
