[{"sura_id":2,"aya_id":102,"segs":[{"y":20,"x":19,"w":1214,"h":112},{"y":153,"x":20,"w":1210,"h":112},{"y":271,"x":20,"w":1211,"h":136},{"y":421,"x":18,"w":1212,"h":113},{"y":544,"x":20,"w":1209,"h":129},{"y":677,"x":18,"w":1213,"h":146},{"y":825,"x":18,"w":1214,"h":122},{"y":961,"x":20,"w":1213,"h":122},{"y":1087,"x":580,"w":650,"h":117}]},{"sura_id":2,"aya_id":103,"segs":[{"y":1087,"x":16,"w":475,"h":117},{"y":1218,"x":92,"w":1139,"h":119}]},{"sura_id":2,"aya_id":104,"segs":[{"y":1353,"x":18,"w":1213,"h":119},{"y":1483,"x":258,"w":974,"h":129}]},{"sura_id":2,"aya_id":105,"segs":[{"y":1501,"x":18,"w":157,"h":102},{"y":1621,"x":19,"w":1213,"h":126},{"y":1759,"x":19,"w":1211,"h":128},{"y":1889,"x":84,"w":1147,"h":128}]}]
