[{"sura_id":2,"aya_id":177,"segs":[{"y":7,"x":14,"w":1223,"h":147},{"y":157,"x":21,"w":1217,"h":116},{"y":294,"x":13,"w":1224,"h":112},{"y":428,"x":14,"w":1224,"h":122},{"y":547,"x":11,"w":1226,"h":144},{"y":684,"x":16,"w":1221,"h":128},{"y":806,"x":651,"w":588,"h":142}]},{"sura_id":2,"aya_id":178,"segs":[{"y":821,"x":18,"w":531,"h":117},{"y":950,"x":19,"w":1219,"h":130},{"y":1089,"x":15,"w":1224,"h":132},{"y":1205,"x":18,"w":1218,"h":158},{"y":1360,"x":701,"w":536,"h":110}]},{"sura_id":2,"aya_id":179,"segs":[{"y":1353,"x":19,"w":603,"h":131},{"y":1496,"x":635,"w":604,"h":116}]},{"sura_id":2,"aya_id":180,"segs":[{"y":1491,"x":12,"w":552,"h":135},{"y":1623,"x":18,"w":1219,"h":130},{"y":1767,"x":613,"w":625,"h":115}]},{"sura_id":2,"aya_id":181,"segs":[{"y":1775,"x":11,"w":511,"h":104},{"y":1893,"x":89,"w":1149,"h":137}]}]
