[{"sura_id":7,"aya_id":138,"segs":[{"y":22,"x":15,"w":1225,"h":127},{"y":149,"x":15,"w":1221,"h":123},{"y":272,"x":423,"w":816,"h":138}]},{"sura_id":7,"aya_id":139,"segs":[{"y":304,"x":14,"w":333,"h":104},{"y":436,"x":369,"w":871,"h":129}]},{"sura_id":7,"aya_id":140,"segs":[{"y":422,"x":15,"w":275,"h":110},{"y":561,"x":343,"w":897,"h":117}]},{"sura_id":7,"aya_id":141,"segs":[{"y":559,"x":14,"w":247,"h":115},{"y":705,"x":15,"w":1225,"h":105},{"y":830,"x":14,"w":1225,"h":140},{"y":988,"x":806,"w":434,"h":101}]},{"sura_id":7,"aya_id":142,"segs":[{"y":974,"x":15,"w":712,"h":102},{"y":1084,"x":13,"w":1226,"h":148},{"y":1226,"x":13,"w":1226,"h":141},{"y":1373,"x":819,"w":421,"h":110}]},{"sura_id":7,"aya_id":143,"segs":[{"y":1369,"x":14,"w":714,"h":111},{"y":1500,"x":10,"w":1228,"h":126},{"y":1641,"x":15,"w":1225,"h":118},{"y":1768,"x":15,"w":1225,"h":122},{"y":1898,"x":91,"w":1148,"h":116}]}]
