[{"sura_id":9,"aya_id":73,"segs":[{"y":23,"x":16,"w":1226,"h":127},{"y":140,"x":521,"w":721,"h":142}]},{"sura_id":9,"aya_id":74,"segs":[{"y":158,"x":15,"w":431,"h":118},{"y":294,"x":15,"w":1227,"h":122},{"y":403,"x":17,"w":1225,"h":139},{"y":551,"x":16,"w":1226,"h":124},{"y":694,"x":6,"w":1236,"h":116},{"y":831,"x":846,"w":396,"h":121}]},{"sura_id":9,"aya_id":75,"segs":[{"y":834,"x":17,"w":749,"h":110},{"y":968,"x":97,"w":1145,"h":109}]},{"sura_id":9,"aya_id":76,"segs":[{"y":1091,"x":16,"w":1227,"h":123},{"y":1243,"x":1011,"w":231,"h":109}]},{"sura_id":9,"aya_id":77,"segs":[{"y":1228,"x":17,"w":904,"h":135},{"y":1361,"x":98,"w":1144,"h":129}]},{"sura_id":9,"aya_id":78,"segs":[{"y":1493,"x":17,"w":1225,"h":117},{"y":1633,"x":922,"w":320,"h":122}]},{"sura_id":9,"aya_id":79,"segs":[{"y":1626,"x":17,"w":817,"h":130},{"y":1762,"x":16,"w":1226,"h":125},{"y":1895,"x":84,"w":1159,"h":118}]}]
