[{"sura_id":11,"aya_id":29,"segs":[{"y":9,"x":17,"w":1218,"h":137},{"y":148,"x":17,"w":1218,"h":133},{"y":302,"x":1061,"w":175,"h":98}]},{"sura_id":11,"aya_id":30,"segs":[{"y":284,"x":17,"w":958,"h":125},{"y":438,"x":924,"w":311,"h":93}]},{"sura_id":11,"aya_id":31,"segs":[{"y":425,"x":17,"w":822,"h":113},{"y":554,"x":14,"w":1221,"h":128},{"y":678,"x":17,"w":1218,"h":153},{"y":826,"x":854,"w":381,"h":124}]},{"sura_id":11,"aya_id":32,"segs":[{"y":832,"x":17,"w":757,"h":130},{"y":962,"x":272,"w":964,"h":117}]},{"sura_id":11,"aya_id":33,"segs":[{"y":975,"x":17,"w":173,"h":104},{"y":1096,"x":302,"w":933,"h":144}]},{"sura_id":11,"aya_id":34,"segs":[{"y":1102,"x":17,"w":212,"h":105},{"y":1228,"x":17,"w":1219,"h":146},{"y":1357,"x":488,"w":747,"h":137}]},{"sura_id":11,"aya_id":35,"segs":[{"y":1350,"x":17,"w":382,"h":150},{"y":1498,"x":102,"w":1133,"h":127}]},{"sura_id":11,"aya_id":36,"segs":[{"y":1622,"x":17,"w":1219,"h":134},{"y":1776,"x":562,"w":673,"h":108}]},{"sura_id":11,"aya_id":37,"segs":[{"y":1768,"x":17,"w":462,"h":143},{"y":1899,"x":93,"w":1143,"h":129}]}]
