[{"sura_id":26,"aya_id":137,"segs":[{"y":14,"x":725,"w":514,"h":122}]},{"sura_id":26,"aya_id":138,"segs":[{"y":24,"x":262,"w":382,"h":111}]},{"sura_id":26,"aya_id":139,"segs":[{"y":24,"x":14,"w":167,"h":100},{"y":137,"x":86,"w":1153,"h":133}]},{"sura_id":26,"aya_id":140,"segs":[{"y":301,"x":677,"w":562,"h":112}]},{"sura_id":26,"aya_id":141,"segs":[{"y":297,"x":138,"w":484,"h":110}]},{"sura_id":26,"aya_id":142,"segs":[{"y":314,"x":14,"w":49,"h":95},{"y":419,"x":588,"w":651,"h":140}]},{"sura_id":26,"aya_id":143,"segs":[{"y":421,"x":86,"w":426,"h":119}]},{"sura_id":26,"aya_id":144,"segs":[{"y":554,"x":800,"w":438,"h":117}]},{"sura_id":26,"aya_id":145,"segs":[{"y":557,"x":11,"w":705,"h":133},{"y":689,"x":807,"w":431,"h":120}]},{"sura_id":26,"aya_id":146,"segs":[{"y":691,"x":84,"w":642,"h":118}]},{"sura_id":26,"aya_id":147,"segs":[{"y":844,"x":857,"w":382,"h":105}]},{"sura_id":26,"aya_id":148,"segs":[{"y":838,"x":80,"w":682,"h":123}]},{"sura_id":26,"aya_id":149,"segs":[{"y":971,"x":550,"w":688,"h":114}]},{"sura_id":26,"aya_id":150,"segs":[{"y":962,"x":85,"w":392,"h":112}]},{"sura_id":26,"aya_id":151,"segs":[{"y":1095,"x":668,"w":570,"h":130}]},{"sura_id":26,"aya_id":152,"segs":[{"y":1093,"x":10,"w":580,"h":121},{"y":1242,"x":955,"w":283,"h":98}]},{"sura_id":26,"aya_id":153,"segs":[{"y":1232,"x":232,"w":639,"h":120}]},{"sura_id":26,"aya_id":154,"segs":[{"y":1234,"x":13,"w":133,"h":89},{"y":1363,"x":171,"w":1068,"h":119}]},{"sura_id":26,"aya_id":155,"segs":[{"y":1380,"x":13,"w":76,"h":86},{"y":1500,"x":343,"w":897,"h":114}]},{"sura_id":26,"aya_id":156,"segs":[{"y":1508,"x":14,"w":254,"h":102},{"y":1630,"x":561,"w":678,"h":132}]},{"sura_id":26,"aya_id":157,"segs":[{"y":1635,"x":13,"w":474,"h":112},{"y":1790,"x":1079,"w":160,"h":82}]},{"sura_id":26,"aya_id":158,"segs":[{"y":1748,"x":14,"w":976,"h":136},{"y":1902,"x":847,"w":391,"h":107}]},{"sura_id":26,"aya_id":159,"segs":[{"y":1911,"x":77,"w":684,"h":112}]}]
