[{"sura_id":33,"aya_id":1,"segs":[{"y":280,"x":15,"w":1224,"h":139},{"y":421,"x":742,"w":497,"h":110}]},{"sura_id":33,"aya_id":2,"segs":[{"y":417,"x":14,"w":643,"h":140},{"y":559,"x":488,"w":751,"h":108}]},{"sura_id":33,"aya_id":3,"segs":[{"y":549,"x":15,"w":386,"h":112},{"y":685,"x":888,"w":351,"h":116}]},{"sura_id":33,"aya_id":4,"segs":[{"y":695,"x":15,"w":793,"h":127},{"y":809,"x":13,"w":1226,"h":131},{"y":940,"x":10,"w":1229,"h":131},{"y":1095,"x":815,"w":424,"h":111}]},{"sura_id":33,"aya_id":5,"segs":[{"y":1084,"x":15,"w":718,"h":123},{"y":1218,"x":14,"w":1227,"h":127},{"y":1354,"x":14,"w":1225,"h":140},{"y":1500,"x":774,"w":464,"h":102}]},{"sura_id":33,"aya_id":6,"segs":[{"y":1490,"x":14,"w":680,"h":132},{"y":1611,"x":14,"w":1225,"h":136},{"y":1756,"x":9,"w":1230,"h":126},{"y":1893,"x":90,"w":1150,"h":123}]}]
